{
    "key": "group_595d0184deced",
    "title": "Testimony Details",
    "fields": [
        {
            "key": "field_595d0f5eebdde",
            "label": "Video hosting platform",
            "name": "testimony_platform",
            "type": "radio",
            "instructions": "",
            "required": 1,
            "conditional_logic": 0,
            "wrapper": {
                "width": "",
                "class": "",
                "id": ""
            },
            "choices": {
                "youtube": "YouTube",
                "vimeo": "Vimeo",
                "other": "Other"
            },
            "allow_null": 1,
            "other_choice": 0,
            "save_other_choice": 0,
            "default_value": "",
            "layout": "horizontal",
            "return_format": "value"
        },
        {
            "key": "field_595d05bfd3748",
            "label": "Video embed",
            "name": "testimony_video_embed",
            "type": "textarea",
            "instructions": "",
            "required": 1,
            "conditional_logic": 0,
            "wrapper": {
                "width": "",
                "class": "",
                "id": ""
            },
            "default_value": "",
            "placeholder": "",
            "maxlength": "",
            "rows": 4,
            "new_lines": ""
        },
        {
            "key": "field_595d08c8d8306",
            "label": "Video ID",
            "name": "testimony_video_id",
            "type": "text",
            "instructions": "Look at the URL of the video page, and at the end of it, you should see a combination of numbers and letters for YouTube and just numbers for Vimeo. This is the code you need to enter.",
            "required": 1,
            "conditional_logic": [
                [
                    {
                        "field": "field_595d0f5eebdde",
                        "operator": "==",
                        "value": "youtube"
                    }
                ],
                [
                    {
                        "field": "field_595d0f5eebdde",
                        "operator": "==",
                        "value": "vimeo"
                    }
                ]
            ],
            "wrapper": {
                "width": "",
                "class": "",
                "id": ""
            },
            "default_value": "",
            "placeholder": "",
            "prepend": "",
            "append": "",
            "maxlength": ""
        }
    ],
    "location": [
        [
            {
                "param": "post_type",
                "operator": "==",
                "value": "testimony"
            }
        ]
    ],
    "menu_order": 0,
    "position": "normal",
    "style": "default",
    "label_placement": "top",
    "instruction_placement": "label",
    "hide_on_screen": [
        "the_content",
        "custom_fields",
        "discussion",
        "comments",
        "revisions",
        "author",
        "format",
        "page_attributes",
        "tags",
        "send-trackbacks"
    ],
    "active": 1,
    "description": "",
    "modified": 1508441788
}